{
    "mappings" : {
        "properties" : {
            "@timestamp" : {
                "type" : "date",
                "index" : false
            },
            "@version" : {
                "type" : "text",
                "index" : false,
                "fields" : {
                    "keyword" : {
                        "type" : "keyword",
                        "ignore_above" : 256
                    }
                }
            },
            "access_right" : {
                "type" : "text",
                "index" : false,
                "fields" : {
                    "keyword" : {
                        "type" : "keyword",
                        "ignore_above" : 256
                    }
                }
            },
            "creators" : {
                "type" : "text",
                "index" : false,
                "fields" : {
                    "keyword" : {
                        "type" : "keyword",
                        "ignore_above" : 256
                    }
                }
            },
            "date_created" : {
                "type" : "date",
                "index" : false
            },
            "date_published" : {
                "type" : "date",
                "index" : false
            },
            "doi" : {
                "type" : "text",
                "index" : false,
                "fields" : {
                    "keyword" : {
                        "type" : "keyword",
                        "ignore_above" : 256
                    }
                }
            },
            "identifier" : {
                "type" : "long",
                "index" : false
            },
            "license_identifier" : {
                "type" : "long",
                "index" : false
            },
            "platform" : {
                "type" : "text",
                "index" : false,
                "fields" : {
                    "keyword" : {
                        "type" : "keyword",
                        "ignore_above" : 256
                    }
                }
            },
            "platform_identifier" : {
                "type" : "text",
                "fields" : {
                    "keyword" : {
                        "type" : "keyword",
                        "ignore_above" : 256
                    }
                }
            },
            "resource_type_identifier" : {
                "type" : "long",
                "index" : false
            },
            "title" : {
                "type" : "text",
                "fields" : {
                    "keyword" : {
                        "type" : "keyword",
                        "ignore_above" : 256
                    }
                }
            },
            "type" : {
                "type" : "text",
                "index" : false,
                "fields" : {
                    "keyword" : {
                        "type" : "keyword",
                        "ignore_above" : 256
                    }
                }
            },
            "url" : {
                "type" : "text",
                "index" : false,
                "fields" : {
                    "keyword" : {
                        "type" : "keyword",
                        "ignore_above" : 256
                    }
                }
            }
        }
    }
}
